eggit/__init__.py
eggit/api_response.py
eggit/converters.py
eggit/egg_enum.py
eggit/egg_string.py
eggit/egg_time.py
eggit/enums.py
eggit/paginator.py
eggit/time_utils.py
tests/__init__.py
tests/test_api_response.py
tests/test_converters.py
tests/test_egg_enum.py
tests/test_egg_string.py
tests/test_egg_time.py
tests/test_enums.py
tests/test_paginator.py
tests/test_time_utils.py
eggit-0.0.26.dist-info/LICENSE
eggit-0.0.26.dist-info/METADATA
eggit-0.0.26.dist-info/WHEEL
eggit-0.0.26.dist-info/top_level.txt
eggit-0.0.26.dist-info/zip-safe
eggit-0.0.26.dist-info/RECORD
