Metadata-Version: 2.1
Name: eggit
Version: 0.0.26
Summary: a python lib
Home-page: https://github.com/MyJoiT/eggit
Author: JoiT
Author-email: myjoit@outlook.com
License: GPL3
Keywords: eggit,lib,tool
Platform: UNKNOWN
